{"_id":"with","_rev":"28-d2330eff98b6a2c380c65e656700f102","name":"with","description":"Compile time `with` for strict mode JavaScript","dist-tags":{"latest":"5.0.0"},"versions":{"1.0.0":{"name":"with","version":"1.0.0","description":"Compile time `with` for strict mode JavaScript","main":"index.js","scripts":{"test":"mocha -R spec"},"repository":{"type":"git","url":"https://github.com/ForbesLindesay/with.git"},"author":{"name":"ForbesLindesay"},"license":"MIT","dependencies":{"lexical-scope":"0.0.11"},"devDependencies":{"mocha":"~1.9.0"},"_id":"with@1.0.0","dist":{"shasum":"ed8fc0c2c5b5a8772db1305940f0b3a8d14c0068","tarball":"http://registry.npmjs.org/with/-/with-1.0.0.tgz"},"_from":".","_npmVersion":"1.2.10","_npmUser":{"name":"forbeslindesay","email":"forbes@lindesay.co.uk"},"maintainers":[{"name":"forbeslindesay","email":"forbes@lindesay.co.uk"}],"directories":{}},"1.0.1":{"name":"with","version":"1.0.1","description":"Compile time `with` for strict mode JavaScript","main":"index.js","scripts":{"test":"mocha -R spec"},"repository":{"type":"git","url":"https://github.com/ForbesLindesay/with.git"},"author":{"name":"ForbesLindesay"},"license":"MIT","dependencies":{"lexical-scope":"0.0.11"},"devDependencies":{"mocha":"~1.9.0"},"_id":"with@1.0.1","dist":{"shasum":"d6ef2fd62fd0022058f55d13af17eede5a7d905e","tarball":"http://registry.npmjs.org/with/-/with-1.0.1.tgz"},"_from":".","_npmVersion":"1.2.10","_npmUser":{"name":"forbeslindesay","email":"forbes@lindesay.co.uk"},"maintainers":[{"name":"forbeslindesay","email":"forbes@lindesay.co.uk"}],"directories":{}},"1.0.2":{"name":"with","version":"1.0.2","description":"Compile time `with` for strict mode JavaScript","main":"index.js","scripts":{"test":"mocha -R spec"},"repository":{"type":"git","url":"https://github.com/ForbesLindesay/with.git"},"author":{"name":"ForbesLindesay"},"license":"MIT","dependencies":{"lexical-scope":"0.0.11"},"devDependencies":{"mocha":"~1.9.0"},"_id":"with@1.0.2","dist":{"shasum":"8e61943446fc4cb1658d416843e635381bd8011a","tarball":"http://registry.npmjs.org/with/-/with-1.0.2.tgz"},"_from":".","_npmVersion":"1.2.10","_npmUser":{"name":"forbeslindesay","email":"forbes@lindesay.co.uk"},"maintainers":[{"name":"forbeslindesay","email":"forbes@lindesay.co.uk"}],"directories":{}},"1.0.3":{"name":"with","version":"1.0.3","description":"Compile time `with` for strict mode JavaScript","main":"index.js","scripts":{"test":"mocha -R spec"},"repository":{"type":"git","url":"https://github.com/ForbesLindesay/with.git"},"author":{"name":"ForbesLindesay"},"license":"MIT","dependencies":{"lexical-scope":"0.0.11"},"devDependencies":{"mocha":"~1.9.0"},"_id":"with@1.0.3","dist":{"shasum":"0eee05e1d49da5eb04467b5343bb49142cbc7be3","tarball":"http://registry.npmjs.org/with/-/with-1.0.3.tgz"},"_from":".","_npmVersion":"1.2.10","_npmUser":{"name":"forbeslindesay","email":"forbes@lindesay.co.uk"},"maintainers":[{"name":"forbeslindesay","email":"forbes@lindesay.co.uk"}],"directories":{}},"1.0.4":{"name":"with","version":"1.0.4","description":"Compile time `with` for strict mode JavaScript","main":"index.js","scripts":{"test":"mocha -R spec"},"repository":{"type":"git","url":"https://github.com/ForbesLindesay/with.git"},"author":{"name":"ForbesLindesay"},"license":"MIT","dependencies":{"lexical-scope":"0.0.12"},"devDependencies":{"mocha":"~1.9.0"},"_id":"with@1.0.4","dist":{"shasum":"67b70e967742b915b1934507628151194e34daeb","tarball":"http://registry.npmjs.org/with/-/with-1.0.4.tgz"},"_from":".","_npmVersion":"1.2.10","_npmUser":{"name":"forbeslindesay","email":"forbes@lindesay.co.uk"},"maintainers":[{"name":"forbeslindesay","email":"forbes@lindesay.co.uk"}],"directories":{}},"1.1.0":{"name":"with","version":"1.1.0","description":"Compile time `with` for strict mode JavaScript","main":"index.js","scripts":{"test":"mocha -R spec"},"repository":{"type":"git","url":"https://github.com/ForbesLindesay/with.git"},"author":{"name":"ForbesLindesay"},"license":"MIT","dependencies":{"uglify-js":"2.3.6"},"devDependencies":{"mocha":"~1.9.0"},"_id":"with@1.1.0","dist":{"shasum":"7f722ce4050ab55310777327b014194c544c66dd","tarball":"http://registry.npmjs.org/with/-/with-1.1.0.tgz"},"_from":".","_npmVersion":"1.2.10","_npmUser":{"name":"forbeslindesay","email":"forbes@lindesay.co.uk"},"maintainers":[{"name":"forbeslindesay","email":"forbes@lindesay.co.uk"}],"directories":{}},"1.1.1":{"name":"with","version":"1.1.1","description":"Compile time `with` for strict mode JavaScript","main":"index.js","scripts":{"test":"mocha -R spec"},"repository":{"type":"git","url":"https://github.com/ForbesLindesay/with.git"},"author":{"name":"ForbesLindesay"},"license":"MIT","dependencies":{"uglify-js":"2.4.0"},"devDependencies":{"mocha":"~1.12.0"},"bugs":{"url":"https://github.com/ForbesLindesay/with/issues"},"_id":"with@1.1.1","dist":{"shasum":"66bd6664deb318b2482dd0424ccdebe822434ac0","tarball":"http://registry.npmjs.org/with/-/with-1.1.1.tgz"},"_from":".","_npmVersion":"1.2.32","_npmUser":{"name":"forbeslindesay","email":"forbes@lindesay.co.uk"},"maintainers":[{"name":"forbeslindesay","email":"forbes@lindesay.co.uk"}],"directories":{}},"2.0.0":{"name":"with","version":"2.0.0","description":"Compile time `with` for strict mode JavaScript","main":"index.js","scripts":{"test":"mocha -R spec"},"repository":{"type":"git","url":"https://github.com/ForbesLindesay/with.git"},"author":{"name":"ForbesLindesay"},"license":"MIT","dependencies":{"uglify-js":"2.4.0"},"devDependencies":{"mocha":"~1.12.0"},"bugs":{"url":"https://github.com/ForbesLindesay/with/issues"},"_id":"with@2.0.0","dist":{"shasum":"ec01ff021db9df05639047147ede012f5e6d0afd","tarball":"http://registry.npmjs.org/with/-/with-2.0.0.tgz"},"_from":".","_npmVersion":"1.3.8","_npmUser":{"name":"forbeslindesay","email":"forbes@lindeay.co.uk"},"maintainers":[{"name":"forbeslindesay","email":"forbes@lindesay.co.uk"}],"directories":{}},"3.0.0":{"name":"with","version":"3.0.0","description":"Compile time `with` for strict mode JavaScript","main":"index.js","scripts":{"test":"mocha -R spec"},"repository":{"type":"git","url":"https://github.com/ForbesLindesay/with.git"},"author":{"name":"ForbesLindesay"},"license":"MIT","dependencies":{"uglify-js":"~2.4.12"},"devDependencies":{"mocha":"~1.12.0"},"bugs":{"url":"https://github.com/ForbesLindesay/with/issues"},"homepage":"https://github.com/ForbesLindesay/with","_id":"with@3.0.0","dist":{"shasum":"38f5d5859bb974c9dad8812372b51dae4b9594cc","tarball":"http://registry.npmjs.org/with/-/with-3.0.0.tgz"},"_from":".","_npmVersion":"1.3.14","_npmUser":{"name":"forbeslindesay","email":"forbes@lindeay.co.uk"},"maintainers":[{"name":"forbeslindesay","email":"forbes@lindesay.co.uk"}],"directories":{}},"3.0.1":{"name":"with","version":"3.0.1","description":"Compile time `with` for strict mode JavaScript","main":"index.js","scripts":{"test":"mocha -R spec"},"repository":{"type":"git","url":"https://github.com/ForbesLindesay/with.git"},"author":{"name":"ForbesLindesay"},"license":"MIT","dependencies":{"uglify-js":"~2.4.12"},"devDependencies":{"mocha":"~1.12.0"},"gitHead":"588a8a3ebeff2b539a2a361449a2c6843566aeda","bugs":{"url":"https://github.com/ForbesLindesay/with/issues"},"homepage":"https://github.com/ForbesLindesay/with","_id":"with@3.0.1","_shasum":"08354da410243cf6173fb142bb04e6c66f96f854","_from":".","_npmVersion":"1.4.21","_npmUser":{"name":"forbeslindesay","email":"forbes@lindeay.co.uk"},"maintainers":[{"name":"forbeslindesay","email":"forbes@lindesay.co.uk"}],"dist":{"shasum":"08354da410243cf6173fb142bb04e6c66f96f854","tarball":"http://registry.npmjs.org/with/-/with-3.0.1.tgz"},"directories":{}},"4.0.0":{"name":"with","version":"4.0.0","description":"Compile time `with` for strict mode JavaScript","main":"index.js","scripts":{"test":"mocha test/index.js -R spec"},"repository":{"type":"git","url":"https://github.com/ForbesLindesay/with.git"},"author":{"name":"ForbesLindesay"},"license":"MIT","dependencies":{"acorn":"^0.8.0","acorn-globals":"^1.0.1"},"devDependencies":{"mocha":"~1.12.0","uglify-js":"^2.4.15"},"gitHead":"4560e51e3bf4016eaf52b4c2156532bceb2bedb1","bugs":{"url":"https://github.com/ForbesLindesay/with/issues"},"homepage":"https://github.com/ForbesLindesay/with","_id":"with@4.0.0","_shasum":"7a78d6642d9b72960a71d1c0c45fd6dd1b878dc7","_from":".","_npmVersion":"1.4.21","_npmUser":{"name":"forbeslindesay","email":"forbes@lindeay.co.uk"},"maintainers":[{"name":"forbeslindesay","email":"forbes@lindesay.co.uk"}],"dist":{"shasum":"7a78d6642d9b72960a71d1c0c45fd6dd1b878dc7","tarball":"http://registry.npmjs.org/with/-/with-4.0.0.tgz"},"directories":{}},"4.0.1":{"name":"with","version":"4.0.1","description":"Compile time `with` for strict mode JavaScript","main":"index.js","scripts":{"test":"mocha test/index.js -R spec"},"repository":{"type":"git","url":"https://github.com/ForbesLindesay/with.git"},"author":{"name":"ForbesLindesay"},"license":"MIT","dependencies":{"acorn":"^0.11.0","acorn-globals":"^1.0.1"},"devDependencies":{"mocha":"~1.12.0","uglify-js":"^2.4.15"},"gitHead":"34b6905f5a2d4c9c483982cb4368f7ec2cdfe7b5","bugs":{"url":"https://github.com/ForbesLindesay/with/issues"},"homepage":"https://github.com/ForbesLindesay/with","_id":"with@4.0.1","_shasum":"accd7a7c321f2d83e303e51c02bb7eb1fff19c32","_from":".","_npmVersion":"1.4.28","_npmUser":{"name":"forbeslindesay","email":"forbes@lindesay.co.uk"},"maintainers":[{"name":"forbeslindesay","email":"forbes@lindesay.co.uk"}],"dist":{"shasum":"accd7a7c321f2d83e303e51c02bb7eb1fff19c32","tarball":"http://registry.npmjs.org/with/-/with-4.0.1.tgz"},"directories":{}},"4.0.2":{"name":"with","version":"4.0.2","description":"Compile time `with` for strict mode JavaScript","main":"index.js","scripts":{"test":"mocha test/index.js -R spec"},"repository":{"type":"git","url":"https://github.com/ForbesLindesay/with.git"},"author":{"name":"ForbesLindesay"},"license":"MIT","dependencies":{"acorn":"^1.0.1","acorn-globals":"^1.0.1"},"devDependencies":{"mocha":"~1.12.0","uglify-js":"^2.4.15"},"gitHead":"0ef234b62e9a6a674e129122efd896a0824e0a44","bugs":{"url":"https://github.com/ForbesLindesay/with/issues"},"homepage":"https://github.com/ForbesLindesay/with","_id":"with@4.0.2","_shasum":"528547b8f394e1ee7d78257e5a810b7b43d65fee","_from":".","_npmVersion":"2.5.1","_nodeVersion":"0.12.0","_npmUser":{"name":"forbeslindesay","email":"forbes@lindesay.co.uk"},"maintainers":[{"name":"forbeslindesay","email":"forbes@lindesay.co.uk"}],"dist":{"shasum":"528547b8f394e1ee7d78257e5a810b7b43d65fee","tarball":"http://registry.npmjs.org/with/-/with-4.0.2.tgz"},"directories":{}},"4.0.3":{"name":"with","version":"4.0.3","description":"Compile time `with` for strict mode JavaScript","main":"index.js","scripts":{"test":"mocha test/index.js -R spec"},"repository":{"type":"git","url":"https://github.com/ForbesLindesay/with.git"},"author":{"name":"ForbesLindesay"},"license":"MIT","dependencies":{"acorn":"^1.0.1","acorn-globals":"^1.0.3"},"devDependencies":{"mocha":"~1.12.0","uglify-js":"^2.4.15"},"gitHead":"38351aea899040937ab8c7c9ce43b3ad1d498bed","bugs":{"url":"https://github.com/ForbesLindesay/with/issues"},"homepage":"https://github.com/ForbesLindesay/with","_id":"with@4.0.3","_shasum":"eefd154e9e79d2c8d3417b647a8f14d9fecce14e","_from":".","_npmVersion":"2.7.1","_nodeVersion":"1.6.2","_npmUser":{"name":"forbeslindesay","email":"forbes@lindesay.co.uk"},"maintainers":[{"name":"forbeslindesay","email":"forbes@lindesay.co.uk"}],"dist":{"shasum":"eefd154e9e79d2c8d3417b647a8f14d9fecce14e","tarball":"http://registry.npmjs.org/with/-/with-4.0.3.tgz"},"directories":{}},"5.0.0":{"name":"with","version":"5.0.0","description":"Compile time `with` for strict mode JavaScript","main":"index.js","scripts":{"test":"mocha test/index.js -R spec"},"repository":{"type":"git","url":"https://github.com/ForbesLindesay/with.git"},"author":{"name":"ForbesLindesay"},"license":"MIT","dependencies":{"acorn":"^1.0.1","acorn-globals":"^1.0.3"},"devDependencies":{"mocha":"~1.12.0","uglify-js":"^2.4.15"},"gitHead":"03b473ddfbc71abe2ed73c0269ec22b30067362d","bugs":{"url":"https://github.com/ForbesLindesay/with/issues"},"homepage":"https://github.com/ForbesLindesay/with","_id":"with@5.0.0","_shasum":"e5b054aa14f7494accc69211387c65c7ac70d415","_from":".","_npmVersion":"2.7.1","_nodeVersion":"1.6.2","_npmUser":{"name":"forbeslindesay","email":"forbes@lindesay.co.uk"},"maintainers":[{"name":"forbeslindesay","email":"forbes@lindesay.co.uk"}],"dist":{"shasum":"e5b054aa14f7494accc69211387c65c7ac70d415","tarball":"http://registry.npmjs.org/with/-/with-5.0.0.tgz"},"directories":{}}},"readme":"# with\n\nCompile time `with` for strict mode JavaScript\n\n[![build status](https://secure.travis-ci.org/ForbesLindesay/with.png)](http://travis-ci.org/ForbesLindesay/with)\n[![Dependency Status](https://img.shields.io/gemnasium/ForbesLindesay/with.svg)](https://gemnasium.com/ForbesLindesay/with)\n[![NPM version](https://img.shields.io/npm/v/with.svg)](http://badge.fury.io/js/with)\n\n## Installation\n\n    $ npm install with\n\n## Usage\n\n```js\nvar addWith = require('with')\n\naddWith('obj', 'console.log(a)')\n// => ';(function (console, a) {\n//       console.log(a)\n//     }(\"console\" in obj ? obj.console :\n//                          typeof console!==\"undefined\" ? console : undefined,\n//       \"a\" in obj ? obj.a :\n//                    typeof a !== \"undefined\" ? a : undefined));'\n\naddWith('obj', 'console.log(a)', ['console'])\n// => ';(function (console, a) {\n//       console.log(a)\n//     }(\"a\" in obj ? obj.a :\n//                    typeof a !== \"undefined\" ? a : undefined));'\n```\n\n## API\n\n### addWith(obj, src[, exclude])\n\nThe idea is that this is roughly equivallent to:\n\n```js\nwith (obj) {\n  src\n}\n```\n\nThere are a few differences though.  For starters, assignments to variables will always remain contained within the with block.\n\ne.g.\n\n```js\nvar foo = 'foo'\nwith ({}) {\n  foo = 'bar'\n}\nassert(foo === 'bar')// => This fails for compile time with but passes for native with\n\nvar obj = {foo: 'foo'}\nwith ({}) {\n  foo = 'bar'\n}\nassert(obj.foo === 'bar')// => This fails for compile time with but passes for native with\n```\n\nIt also makes everything be declared, so you can always do:\n\n```js\nif (foo === undefined)\n```\n\ninstead of\n\n```js\nif (typeof foo === 'undefined')\n```\n\nThis is not the case if foo is in `exclude`.  If a variable is excluded, we ignore it entirely.  This is useful if you know a variable will be global as it can lead to efficiency improvements.\n\nIt is also safe to use in strict mode (unlike `with`) and it minifies properly (`with` disables virtually all minification).\n\n## License\n\n  MIT","maintainers":[{"name":"forbeslindesay","email":"forbes@lindesay.co.uk"}],"time":{"modified":"2015-04-08T22:42:23.299Z","created":"2013-05-21T09:59:05.355Z","1.0.0":"2013-05-21T09:59:07.739Z","1.0.1":"2013-05-21T10:05:18.949Z","1.0.2":"2013-05-21T10:09:32.988Z","1.0.3":"2013-05-24T18:11:14.397Z","1.0.4":"2013-05-31T16:01:01.164Z","1.1.0":"2013-06-16T01:32:57.310Z","1.1.1":"2013-08-25T01:55:46.202Z","2.0.0":"2013-10-01T09:17:48.479Z","3.0.0":"2014-02-03T14:28:38.318Z","3.0.1":"2014-08-19T17:05:27.350Z","4.0.0":"2014-09-22T16:22:10.195Z","4.0.1":"2015-02-07T22:47:22.032Z","4.0.2":"2015-03-29T00:21:32.381Z","4.0.3":"2015-04-06T21:17:47.492Z","5.0.0":"2015-04-08T22:42:23.299Z"},"author":{"name":"ForbesLindesay"},"repository":{"type":"git","url":"https://github.com/ForbesLindesay/with.git"},"readmeFilename":"README.md","homepage":"https://github.com/ForbesLindesay/with","bugs":{"url":"https://github.com/ForbesLindesay/with/issues"},"license":"MIT","_attachments":{},"_etag":"\"7HEPY42G9QCVGYZC86LJ7P5IP\""}