{"_id":"babylon","_rev":"5-624c9b0185dbdec1770164e4e72fcad6","name":"babylon","dist-tags":{"latest":"5.7.2"},"versions":{"0.0.1":{"name":"babylon","version":"0.0.1","description":"","main":"index.js","scripts":{"test":"echo \"Error: no test specified\" && exit 1"},"repository":{"type":"git","url":"git+https://github.com/babel/babylon.git"},"author":"","license":"ISC","bugs":{"url":"https://github.com/babel/babylon/issues"},"homepage":"https://github.com/babel/babylon#readme","_id":"babylon@0.0.1","_shasum":"683be72d7c1cfb5a21193ff7eb1ea04b529ab5ed","_from":".","_npmVersion":"3.1.0","_nodeVersion":"2.0.0","_npmUser":{"name":"sebmck","email":"sebmck@gmail.com"},"maintainers":[{"name":"sebmck","email":"sebmck@gmail.com"}],"dist":{"shasum":"683be72d7c1cfb5a21193ff7eb1ea04b529ab5ed","tarball":"http://registry.npmjs.org/babylon/-/babylon-0.0.1.tgz"},"directories":{}},"5.6.23":{"name":"babylon","version":"5.6.23","description":"<p align=\"center\">   <img alt=\"babylon\" src=\"https://raw.githubusercontent.com/babel/logo/master/babylon.png\" width=\"700\"> </p>","author":{"name":"Sebastian McKenzie","email":"sebmck@gmail.com"},"homepage":"https://babeljs.io/","license":"MIT","repository":{"type":"git","url":"git+https://github.com/babel/babel.git"},"main":"lib/index.js","bugs":{"url":"https://github.com/babel/babel/issues"},"_id":"babylon@5.6.23","scripts":{},"_shasum":"645bff303c1317f79d0212409075d7f2c08dd033","_from":".","_npmVersion":"3.1.0","_nodeVersion":"2.0.0","_npmUser":{"name":"sebmck","email":"sebmck@gmail.com"},"maintainers":[{"name":"sebmck","email":"sebmck@gmail.com"}],"dist":{"shasum":"645bff303c1317f79d0212409075d7f2c08dd033","tarball":"http://registry.npmjs.org/babylon/-/babylon-5.6.23.tgz"},"directories":{}},"5.7.1":{"name":"babylon","version":"5.7.1","description":"<p align=\"center\">   <img alt=\"babylon\" src=\"https://raw.githubusercontent.com/babel/logo/master/babylon.png\" width=\"700\"> </p>","author":{"name":"Sebastian McKenzie","email":"sebmck@gmail.com"},"homepage":"https://babeljs.io/","license":"MIT","repository":{"type":"git","url":"git+https://github.com/babel/babel.git"},"main":"lib/index.js","bugs":{"url":"https://github.com/babel/babel/issues"},"_id":"babylon@5.7.1","scripts":{},"_shasum":"7242fffe98a0ebd3786ba1c350658a63d95c7d8a","_from":".","_npmVersion":"3.1.0","_nodeVersion":"2.0.0","_npmUser":{"name":"sebmck","email":"sebmck@gmail.com"},"maintainers":[{"name":"sebmck","email":"sebmck@gmail.com"}],"dist":{"shasum":"7242fffe98a0ebd3786ba1c350658a63d95c7d8a","tarball":"http://registry.npmjs.org/babylon/-/babylon-5.7.1.tgz"},"directories":{}},"5.7.2":{"name":"babylon","version":"5.7.2","description":"<p align=\"center\">   <img alt=\"babylon\" src=\"https://raw.githubusercontent.com/babel/logo/master/babylon.png\" width=\"700\"> </p>","author":{"name":"Sebastian McKenzie","email":"sebmck@gmail.com"},"homepage":"https://babeljs.io/","license":"MIT","repository":{"type":"git","url":"git+https://github.com/babel/babel.git"},"main":"lib/index.js","bugs":{"url":"https://github.com/babel/babel/issues"},"_id":"babylon@5.7.2","scripts":{},"_shasum":"8043aad297ce07f40984a6f546c96068905db386","_from":".","_npmVersion":"3.1.0","_nodeVersion":"2.0.0","_npmUser":{"name":"sebmck","email":"sebmck@gmail.com"},"maintainers":[{"name":"sebmck","email":"sebmck@gmail.com"}],"dist":{"shasum":"8043aad297ce07f40984a6f546c96068905db386","tarball":"http://registry.npmjs.org/babylon/-/babylon-5.7.2.tgz"},"directories":{}}},"readme":"<p align=\"center\">\n  <img alt=\"babylon\" src=\"https://raw.githubusercontent.com/babel/logo/master/babylon.png\" width=\"700\">\n</p>\n\n<p align=\"center\">\n  Babylon is a JavaScript parser used in <a href=\"https://github.com/babel/babel\">Babel</a>.\n</p>\n\n## Credits\n\nHeavily based on [acorn](https://github.com/marijnh/acorn) and [acorn-jsx](https://github.com/RReverser/acorn-jsx),\nthanks to the awesome work of [@RReverser](https://github.com/RReverser) and [@marijnh](https://github.com/marijnh).\n\nSignificant diversions are expected to occur in the future such as streaming, EBNF definitions, sweet.js integration,\ninterspacial parsing, comment attachment and more.\n","maintainers":[{"name":"sebmck","email":"sebmck@gmail.com"}],"time":{"modified":"2015-07-15T19:36:18.446Z","created":"2015-07-10T14:51:18.324Z","0.0.1":"2015-07-10T14:51:18.324Z","5.6.23":"2015-07-15T10:55:44.088Z","5.7.1":"2015-07-15T16:09:42.190Z","5.7.2":"2015-07-15T19:36:18.446Z"},"homepage":"https://babeljs.io/","repository":{"type":"git","url":"git+https://github.com/babel/babel.git"},"bugs":{"url":"https://github.com/babel/babel/issues"},"license":"MIT","readmeFilename":"README.md","description":"<p align=\"center\">   <img alt=\"babylon\" src=\"https://raw.githubusercontent.com/babel/logo/master/babylon.png\" width=\"700\"> </p>","author":{"name":"Sebastian McKenzie","email":"sebmck@gmail.com"},"users":{"mathieumg":true},"_attachments":{},"_etag":"\"DV0X32IRLEKBQK08G5ROUJ1VW\""}